{
    "category": "Layers",
    "description": "@@TODO: This sample demonstrates how to show labels on feature layers.",
    "ignore": false,
    "images": [
        "image1.png"
    ],
    "keywords": [
        "@@TODO: *** PLEASE ADD ADDITIONAL KEYWORDS ***"
    ],
    "redirect_from": "@@TODO: /ios/latest/swift/sample-code/show-labels-on-layers.htm",
    "relevant_apis": [
        "@@TODO: *** PLEASE ADD RELEVANT APIS ***"
    ],
    "snippets": [
        "@@TODO: *** PLEASE VERIFY THE INCLUSION OF THESE SNIPPETS ***",
        "ShowLabelsOnLayersViewController.swift"
    ],
    "title": "@@TODO: Show labels on layers"
}
