{
    "category": "Maps",
    "description": "Determine the map's load status which can be `notLoaded`, `failedToLoad`, `loading`, or `loaded`.",
    "ignore": false,
    "images": [
        "map-load-status.png"
    ],
    "keywords": [
        "loadStatus",
        "loadable pattern",
        "map",
        "AGSLoadStatus",
        "AGSMap",
        "AGSMapView"
    ],
    "redirect_from": [
        "/ios/latest/swift/sample-code/map-loaded.htm"
    ],
    "relevant_apis": [
        "AGSLoadStatus",
        "AGSMap",
        "AGSMapView"
    ],
    "snippets": [
        "MapLoadedViewController.swift"
    ],
    "title": "Map load status"
}
