{
    "category": "Features",
    "description": "Find features in a feature table which match an SQL query.",
    "ignore": false,
    "images": [
        "feature-layer-query-1.png",
        "feature-layer-query-2.png"
    ],
    "keywords": [
        "query",
        "search",
        "AGSFeatureLayer",
        "AGSFeatureQueryResult",
        "AGSQueryParameters",
        "AGSServiceFeatureTable"
    ],
    "redirect_from": [
        "/ios/latest/swift/sample-code/feature-layer-query.htm"
    ],
    "relevant_apis": [
        "AGSFeatureLayer",
        "AGSFeatureQueryResult",
        "AGSQueryParameters",
        "AGSServiceFeatureTable"
    ],
    "snippets": [
        "FLQueryViewController.swift"
    ],
    "title": "Feature layer query"
}
