{
    "category": "Edit data",
    "description": "Update feature attributes in an online feature service.",
    "ignore": false,
    "images": [
        "update-attributes-4.png",
        "update-attributes-3.png",
        "update-attributes-2.png",
        "update-attributes-1.png"
    ],
    "keywords": [
        "amend",
        "attribute",
        "details",
        "edit",
        "editing",
        "information",
        "value",
        "AGSArcGISFeature",
        "AGSFeatureLayer",
        "AGSServiceFeatureTable"
    ],
    "redirect_from": [
        "/ios/latest/swift/sample-code/update-attributes-feature-service-.htm"
    ],
    "relevant_apis": [
        "AGSArcGISFeature",
        "AGSFeatureLayer",
        "AGSServiceFeatureTable"
    ],
    "snippets": [
        "UpdateAttributesOptionsViewController.swift",
        "UpdateAttributesViewController.swift"
    ],
    "title": "Update attributes (feature service)"
}